{
  "_class": "symbolInstance",
  "booleanOperation": -1,
  "do_objectID": "F0A6AE49-0D97-4BA8-94C4-4B3EFD0ABF7B",
  "exportOptions": {
    "_class": "exportOptions",
    "do_objectID": "964F1CC7-5732-4A2E-9B97-5388722377CB",
    "exportFormats": [
    ],
    "includedLayerIds": [
    ],
    "layerOptions": 0,
    "shouldTrim": false
  },
  "frame": {
    "_class": "rect",
    "constrainProportions": false,
    "do_objectID": "7E8A2288-BB42-42F4-9050-4A33FA464DAC",
    "height": 20,
    "width": 21,
    "x": 0,
    "y": 5
  },
  "horizontalSpacing": 0,
  "isFixedToViewport": false,
  "isFlippedHorizontal": false,
  "isFlippedVertical": false,
  "isLocked": false,
  "isVisible": true,
  "layerListExpandedType": 0,
  "name": "icons/cheveron-outline-right copy",
  "nameIsFixed": false,
  "overrideValues": [
    {
      "_class": "overrideValue",
      "do_objectID": "D2F76708-4BDE-4B6D-8336-470791425967",
      "overrideName": "67E33BB8-1204-484E-8F8F-7E3BCBBAA301_symbolID",
      "value": "0AB2C46B-2F53-423F-BC0C-65C8B0405990"
    }
  ],
  "resizingConstraint": 63,
  "resizingType": 0,
  "rotation": 0,
  "scale": 1,
  "shouldBreakMaskChain": false,
  "style": {
    "_class": "style",
    "do_objectID": "F9FC91D1-1E42-4309-9736-C1C57C424671",
    "endMarkerType": 0,
    "miterLimit": 10,
    "startMarkerType": 0,
    "windingRule": 1
  },
  "symbolID": "0F79BD4D-088A-4A17-AEA2-895F1E6C7EFB",
  "userInfo": {
    "com.animaapp.stc-sketch-plugin": {
      "kModelPropertiesKey": {
      }
    }
  },
  "verticalSpacing": 0
}