{
  "_class": "rectangle",
  "booleanOperation": -1,
  "clippingMaskMode": 0,
  "do_objectID": "A49F80EB-2303-4CBB-8F09-5AE3346DAFB6",
  "edited": false,
  "exportOptions": {
    "_class": "exportOptions",
    "do_objectID": "092311A6-6873-439B-A373-4476A640A73D",
    "exportFormats": [
    ],
    "includedLayerIds": [
    ],
    "layerOptions": 0,
    "shouldTrim": false
  },
  "fixedRadius": 0,
  "frame": {
    "_class": "rect",
    "constrainProportions": false,
    "do_objectID": "1C124C5A-D8A8-4AED-BAC3-83EBF4B766D0",
    "height": 199.9999999999999,
    "width": 200,
    "x": -2.842170943040401e-14,
    "y": -5.684341886080801e-14
  },
  "hasClippingMask": false,
  "hasConvertedToNewRoundCorners": true,
  "isClosed": true,
  "isFixedToViewport": false,
  "isFlippedHorizontal": false,
  "isFlippedVertical": false,
  "isLocked": false,
  "isVisible": true,
  "layerListExpandedType": 1,
  "name": "Color",
  "nameIsFixed": true,
  "pointRadiusBehaviour": 0,
  "points": [
    {
      "_class": "curvePoint",
      "cornerRadius": 0,
      "curveFrom": "{0, 0}",
      "curveMode": 1,
      "curveTo": "{0, 0}",
      "hasCurveFrom": false,
      "hasCurveTo": false,
      "point": "{0, 0}"
    },
    {
      "_class": "curvePoint",
      "cornerRadius": 0,
      "curveFrom": "{1, 0}",
      "curveMode": 1,
      "curveTo": "{1, 0}",
      "hasCurveFrom": false,
      "hasCurveTo": false,
      "point": "{1, 0}"
    },
    {
      "_class": "curvePoint",
      "cornerRadius": 0,
      "curveFrom": "{1, 1}",
      "curveMode": 1,
      "curveTo": "{1, 1}",
      "hasCurveFrom": false,
      "hasCurveTo": false,
      "point": "{1, 1}"
    },
    {
      "_class": "curvePoint",
      "cornerRadius": 0,
      "curveFrom": "{0, 1}",
      "curveMode": 1,
      "curveTo": "{0, 1}",
      "hasCurveFrom": false,
      "hasCurveTo": false,
      "point": "{0, 1}"
    }
  ],
  "resizingConstraint": 63,
  "resizingType": 0,
  "rotation": 0,
  "sharedStyleID": "1FCFAAE0-D5B8-4313-B366-2E774D30B65E",
  "shouldBreakMaskChain": false,
  "style": {
    "_class": "style",
    "do_objectID": "2B4C9144-9E01-4FC7-844F-C74A6CD221F0",
    "endMarkerType": 0,
    "fills": [
      {
        "_class": "fill",
        "color": {
          "_class": "color",
          "alpha": 1,
          "blue": 0.4,
          "green": 0.3568627450980392,
          "red": 0.3098039215686275
        },
        "fillType": 0,
        "isEnabled": true,
        "noiseIndex": 0,
        "noiseIntensity": 0,
        "patternFillType": 1,
        "patternTileScale": 1
      }
    ],
    "miterLimit": 10,
    "startMarkerType": 0,
    "windingRule": 1
  },
  "userInfo": {
    "com.animaapp.stc-sketch-plugin": {
      "kModelPropertiesKey": {
      }
    }
  }
}