{
  "_class": "group",
  "booleanOperation": -1,
  "do_objectID": "DAA1DBBC-4318-4DB2-97C6-E0E5CBD596FE",
  "exportOptions": {
    "_class": "exportOptions",
    "exportFormats": [
    ],
    "includedLayerIds": [
    ],
    "layerOptions": 0,
    "shouldTrim": false
  },
  "frame": {
    "_class": "rect",
    "constrainProportions": false,
    "height": 270,
    "width": 270,
    "x": 1035,
    "y": 480
  },
  "hasClickThrough": false,
  "isFixedToViewport": false,
  "isFlippedHorizontal": false,
  "isFlippedVertical": false,
  "isLocked": false,
  "isVisible": false,
  "layerListExpandedType": 0,
  "layers": [
    {
      "class": "shapeGroup",
      "id": "36DC01F1-215B-48E5-8F2D-53020384FE8B"
    },
    {
      "class": "bitmap",
      "id": "ED812F80-1D41-4AC9-88B5-E375599C561F"
    },
    {
      "class": "group",
      "id": "FB2691C0-781F-44A2-9A4F-0699ECE0A1AA"
    },
    {
      "class": "symbolInstance",
      "id": "65ADAE50-60DB-4E78-9F4E-34FA6DD15711"
    }
  ],
  "name": "Sponsor",
  "nameIsFixed": true,
  "resizingConstraint": 63,
  "resizingType": 0,
  "rotation": 0,
  "shouldBreakMaskChain": false,
  "style": {
    "_class": "style",
    "endMarkerType": 0,
    "miterLimit": 10,
    "startMarkerType": 0,
    "windingRule": 1
  },
  "userInfo": {
    "com.animaapp.stc-sketch-plugin": {
      "kModelPropertiesKey": {
      }
    }
  }
}