{
  "_class": "symbolInstance",
  "booleanOperation": 0,
  "do_objectID": "241882FE-78AB-4D83-B075-400349DCB309",
  "exportOptions": {
    "_class": "exportOptions",
    "do_objectID": "3F340433-4F9A-4783-9944-13AA277A3D9D",
    "exportFormats": [
    ],
    "includedLayerIds": [
    ],
    "layerOptions": 0,
    "shouldTrim": false
  },
  "frame": {
    "_class": "rect",
    "constrainProportions": false,
    "do_objectID": "37F0F6CC-EA1D-410A-BA56-828C03A6EE13",
    "height": 80,
    "width": 170,
    "x": 0,
    "y": 0
  },
  "horizontalSpacing": 0,
  "isFixedToViewport": false,
  "isFlippedHorizontal": false,
  "isFlippedVertical": false,
  "isLocked": false,
  "isVisible": true,
  "layerListExpandedType": 0,
  "name": "colors/gray-lite",
  "nameIsFixed": false,
  "overrideValues": [
  ],
  "resizingConstraint": 63,
  "resizingType": 0,
  "rotation": 0,
  "scale": 1,
  "shouldBreakMaskChain": false,
  "style": {
    "_class": "style",
    "do_objectID": "9D809BDE-2C58-4C51-9689-D5F3C52AE070",
    "endMarkerType": 0,
    "miterLimit": 10,
    "startMarkerType": 0,
    "windingRule": 1
  },
  "symbolID": "690F1706-6064-4124-82D6-04B493086BD9",
  "userInfo": {
    "com.animaapp.stc-sketch-plugin": {
      "kModelPropertiesKey": {
      }
    }
  },
  "verticalSpacing": 0
}